depthai_nodes/__init__.py
depthai_nodes/constants.py
depthai_nodes/logging.py
depthai_nodes/message/__init__.py
depthai_nodes/message/classification.py
depthai_nodes/message/clusters.py
depthai_nodes/message/gathered_data.py
depthai_nodes/message/img_detections.py
depthai_nodes/message/keypoints.py
depthai_nodes/message/lines.py
depthai_nodes/message/map.py
depthai_nodes/message/prediction.py
depthai_nodes/message/segmentation.py
depthai_nodes/message/creators/__init__.py
depthai_nodes/message/creators/classification.py
depthai_nodes/message/creators/clusters.py
depthai_nodes/message/creators/detection.py
depthai_nodes/message/creators/image.py
depthai_nodes/message/creators/keypoints.py
depthai_nodes/message/creators/line.py
depthai_nodes/message/creators/map.py
depthai_nodes/message/creators/regression.py
depthai_nodes/message/creators/segmentation.py
depthai_nodes/message/creators/tracked_features.py
depthai_nodes/message/utils/__init__.py
depthai_nodes/message/utils/copy_message.py
depthai_nodes/message/utils/detection_utils.py
depthai_nodes/node/__init__.py
depthai_nodes/node/apply_colormap.py
depthai_nodes/node/base_host_node.py
depthai_nodes/node/depth_merger.py
depthai_nodes/node/detection_cropper.py
depthai_nodes/node/gather_data.py
depthai_nodes/node/host_parsing_neural_network.py
depthai_nodes/node/host_spatials_calc.py
depthai_nodes/node/img_detections_bridge.py
depthai_nodes/node/img_detections_filter.py
depthai_nodes/node/img_frame_overlay.py
depthai_nodes/node/parser_generator.py
depthai_nodes/node/parsing_neural_network.py
depthai_nodes/node/snaps_producer.py
depthai_nodes/node/tiles_patcher.py
depthai_nodes/node/tiling.py
depthai_nodes/node/parsers/__init__.py
depthai_nodes/node/parsers/base_parser.py
depthai_nodes/node/parsers/classification.py
depthai_nodes/node/parsers/classification_sequence.py
depthai_nodes/node/parsers/detection.py
depthai_nodes/node/parsers/embeddings.py
depthai_nodes/node/parsers/fastsam.py
depthai_nodes-0.3.5.dist-info/LICENSE
depthai_nodes-0.3.5.dist-info/METADATA
depthai_nodes-0.3.5.dist-info/WHEEL
depthai_nodes-0.3.5.dist-info/top_level.txt
depthai_nodes-0.3.5.dist-info/RECORD
