Metadata-Version: 2.1
Name: depthai-nodes
Version: 0.3.5
Summary: Community on-host nodes for DepthAI.
Author-email: Luxonis <support@luxonis.com>
Maintainer-email: Luxonis <support@luxonis.com>
License: Apache License
Project-URL: repository, https://github.com/luxonis/depthai-nodes
Project-URL: issues, https://github.com/luxonis/depthai-nodes/issues
Keywords: ml,postprocessing,luxonis,oak
Classifier: License :: OSI Approved :: Apache Software License
Classifier: Development Status :: 3 - Alpha
Classifier: Programming Language :: Python :: 3.8
Classifier: Topic :: Scientific/Engineering :: Artificial Intelligence
Classifier: Topic :: Scientific/Engineering :: Image Processing
Classifier: Topic :: Scientific/Engineering :: Image Recognition
Requires-Python: >=3.8
License-File: LICENSE
Requires-Dist: depthai>=3.0.0
Requires-Dist: opencv-python-headless~=4.10.0
Requires-Dist: numpy>=1.22
Provides-Extra: dev
Requires-Dist: pre-commit<4.0.0,>=3.2.1; extra == "dev"
Requires-Dist: pydoctor; extra == "dev"
Requires-Dist: pytest-dependency>=0.6.0; extra == "dev"
Requires-Dist: pytest-cov>=4.1.0; extra == "dev"
Requires-Dist: pytest-subtests>=0.12.1; extra == "dev"
Requires-Dist: pytest-md>=0.2.0; extra == "dev"
Requires-Dist: coverage-badge>=1.1.0; extra == "dev"
Requires-Dist: b2==3.16.1; extra == "dev"
Requires-Dist: pytest-xdist; extra == "dev"
